var/__init__.py
var/__version__.py
var/auxiliary.py
var/methods.py
var/var.py
var/.info/CHANGELOG
var/.version/version.dat
var/data/data.csv
var-0.0.5.dist-info/LICENSE
var-0.0.5.dist-info/METADATA
var-0.0.5.dist-info/WHEEL
var-0.0.5.dist-info/top_level.txt
var-0.0.5.dist-info/RECORD
