Metadata-Version: 2.1
Name: var
Version: 0.0.5
Summary: Different Methods to Estimate the Value-at-Risk of a portfolio.
Home-page: https://github.com/ibaris/VaR
Author: Ismail Baris
Author-email: i.baris@outlook.de
Maintainer: Ismail Baris
License: UNKNOWN
Platform: UNKNOWN
Classifier: Intended Audience :: Science/Research
Classifier: Intended Audience :: Developers
Classifier: Intended Audience :: Education
Classifier: Intended Audience :: End Users/Desktop
Classifier: Programming Language :: Python :: 3.7
Classifier: Operating System :: Microsoft
